LICENSE
README.md
setup.py
flowcontainer/__init__.py
flowcontainer/extractor.py
flowcontainer/flow_generator.py
flowcontainer/flows.py
flowcontainer/network_destination.py
flowcontainer/reader.py
flowcontainer/split_pcap.py
flowcontainer.egg-info/PKG-INFO
flowcontainer.egg-info/SOURCES.txt
flowcontainer.egg-info/dependency_links.txt
flowcontainer.egg-info/top_level.txt